magiccube/__init__.py
magiccube/cube.py
magiccube/cube_base.py
magiccube/cube_move.py
magiccube/cube_piece.py
magiccube/cube_print.py
magiccube/optimizer/move_optimizer.py
magiccube/solver/__init__.py
magiccube/solver/basic/__init__.py
magiccube/solver/basic/basic_solver.py
magiccube/solver/basic/solver_base.py
magiccube/solver/basic/solver_stages.py
magiccube-1.2.0.dist-info/licenses/LICENSE
magiccube-1.2.0.dist-info/METADATA
magiccube-1.2.0.dist-info/WHEEL
magiccube-1.2.0.dist-info/top_level.txt
magiccube-1.2.0.dist-info/RECORD
