Metadata-Version: 2.4
Name: magiccube
Version: 1.2.0
Summary: NxNxN Rubik Cube implementation
Author-email: Gonçalo Trincão Cunha <goncalo.cunha@gmail.com>
License: BSD-3-Clause
Project-URL: Homepage, https://github.com/trincaog/magiccube
Keywords: rubik,cube,solver,Rubik Cube,NxNxN
Classifier: Programming Language :: Python :: 3
Classifier: Development Status :: 5 - Production/Stable
Classifier: Operating System :: OS Independent
Requires-Python: >=3.9
License-File: LICENSE
Requires-Dist: numpy
Dynamic: license-file
